slider_pmf/__init__.py
slider_pmf/slider.py
slider_pmf-0.0.1.dist-info/LICENSE
slider_pmf-0.0.1.dist-info/METADATA
slider_pmf-0.0.1.dist-info/WHEEL
slider_pmf-0.0.1.dist-info/top_level.txt
slider_pmf-0.0.1.dist-info/RECORD
