Metadata-Version: 2.1
Name: slider-pmf
Version: 0.0.1
Summary: A Slider for tkinter library
Author-email: Mohammad Pourmohammadi Fallah <mohammad.pfallah@gmail.com>
License: Copyright (c) 2022 Mohammad Pourmohammadi Fallah        
Classifier: Programming Language :: Python :: 3
Classifier: License :: OSI Approved :: MIT License
Classifier: Operating System :: OS Independent
Requires-Python: >=3.7
License-File: LICENSE
